{"0":{"PartialDate(dd=1, mm=1)":11.074395,"PartialDate(dd=2, mm=1)":10.546404,"PartialDate(dd=3, mm=1)":10.347367,"PartialDate(dd=4, mm=1)":11.450473,"PartialDate(dd=5, mm=1)":11.760382,"PartialDate(dd=6, mm=1)":12.541599,"PartialDate(dd=7, mm=1)":12.541599,"PartialDate(dd=8, mm=1)":12.541599,"PartialDate(dd=9, mm=1)":11.1267,"PartialDate(dd=10, mm=1)":12.231895,"PartialDate(dd=11, mm=1)":12.343284,"PartialDate(dd=12, mm=1)":12.5621605,"PartialDate(dd=13, mm=1)":11.969079,"PartialDate(dd=14, mm=1)":11.969079,"PartialDate(dd=15, mm=1)":11.969079,"PartialDate(dd=16, mm=1)":12.330765,"PartialDate(dd=17, mm=1)":11.390043,"PartialDate(dd=18, mm=1)":10.734003,"PartialDate(dd=19, mm=1)":11.062167,"PartialDate(dd=20, mm=1)":11.534524,"PartialDate(dd=21, mm=1)":11.534524,"PartialDate(dd=22, mm=1)":11.534524,"PartialDate(dd=23, mm=1)":10.99216,"PartialDate(dd=24, mm=1)":10.989936,"PartialDate(dd=25, mm=1)":12.313714,"PartialDate(dd=26, mm=1)":12.313714,"PartialDate(dd=27, mm=1)":14.035179,"PartialDate(dd=28, mm=1)":14.035179,"PartialDate(dd=29, mm=1)":14.035179,"PartialDate(dd=30, mm=1)":13.745202,"PartialDate(dd=31, mm=1)":13.697394,"PartialDate(dd=1, mm=2)":13.546108,"PartialDate(dd=2, mm=2)":13.282887,"PartialDate(dd=3, mm=2)":11.857302,"PartialDate(dd=4, mm=2)":11.857302,"PartialDate(dd=5, mm=2)":11.857302,"PartialDate(dd=6, mm=2)":12.445773,"PartialDate(dd=7, mm=2)":12.804817,"PartialDate(dd=8, mm=2)":12.064094,"PartialDate(dd=9, mm=2)":11.809949,"PartialDate(dd=10, mm=2)":12.025618,"PartialDate(dd=11, mm=2)":12.025618,"PartialDate(dd=12, mm=2)":12.025618,"PartialDate(dd=13, mm=2)":12.490239,"PartialDate(dd=14, mm=2)":11.536769,"PartialDate(dd=15, mm=2)":10.928893,"PartialDate(dd=16, mm=2)":10.8313675,"PartialDate(dd=17, mm=2)":11.358733,"PartialDate(dd=18, mm=2)":11.358733,"PartialDate(dd=19, mm=2)":11.358733,"PartialDate(dd=20, mm=2)":11.955522,"PartialDate(dd=21, mm=2)":12.060694,"PartialDate(dd=22, mm=2)":13.714878,"PartialDate(dd=23, mm=2)":13.997684,"PartialDate(dd=24, mm=2)":14.272468,"PartialDate(dd=25, mm=2)":14.272468,"PartialDate(dd=26, mm=2)":14.272468,"PartialDate(dd=27, mm=2)":14.677674,"PartialDate(dd=28, mm=2)":15.380221,"PartialDate(dd=1, mm=3)":14.467035,"PartialDate(dd=2, mm=3)":15.347831,"PartialDate(dd=3, mm=3)":13.730033,"PartialDate(dd=4, mm=3)":13.730033,"PartialDate(dd=5, mm=3)":13.730033,"PartialDate(dd=6, mm=3)":13.042775,"PartialDate(dd=7, mm=3)":13.042775,"PartialDate(dd=8, mm=3)":12.80253,"PartialDate(dd=9, mm=3)":13.838577,"PartialDate(dd=10, mm=3)":14.954558,"PartialDate(dd=11, mm=3)":14.954558,"PartialDate(dd=12, mm=3)":14.954558,"PartialDate(dd=13, mm=3)":16.703321,"PartialDate(dd=14, mm=3)":17.387493,"PartialDate(dd=15, mm=3)":17.93913,"PartialDate(dd=16, mm=3)":17.860186,"PartialDate(dd=17, mm=3)":17.093819,"PartialDate(dd=18, mm=3)":17.093819,"PartialDate(dd=19, mm=3)":17.093819,"PartialDate(dd=20, mm=3)":17.836391,"PartialDate(dd=21, mm=3)":17.008598,"PartialDate(dd=22, mm=3)":17.008598,"PartialDate(dd=23, mm=3)":17.15071,"PartialDate(dd=24, mm=3)":18.055851,"PartialDate(dd=25, mm=3)":18.055851,"PartialDate(dd=26, mm=3)":18.055851,"PartialDate(dd=27, mm=3)":17.78885,"PartialDate(dd=28, mm=3)":17.984291,"PartialDate(dd=29, mm=3)":17.169271,"PartialDate(dd=30, mm=3)":17.169271,"PartialDate(dd=31, mm=3)":15.352624,"PartialDate(dd=1, mm=4)":15.352624,"PartialDate(dd=2, mm=4)":15.352624,"PartialDate(dd=3, mm=4)":15.040396,"PartialDate(dd=4, mm=4)":15.040396,"PartialDate(dd=5, mm=4)":14.117297,"PartialDate(dd=6, mm=4)":13.893508,"PartialDate(dd=7, mm=4)":13.893508,"PartialDate(dd=8, mm=4)":13.893508,"PartialDate(dd=9, mm=4)":13.893508,"PartialDate(dd=10, mm=4)":13.782532,"PartialDate(dd=11, mm=4)":13.16386,"PartialDate(dd=12, mm=4)":12.705112,"PartialDate(dd=13, mm=4)":12.596429,"PartialDate(dd=14, mm=4)":12.596429,"PartialDate(dd=15, mm=4)":12.596429,"PartialDate(dd=16, mm=4)":12.596429,"PartialDate(dd=17, mm=4)":13.279423,"PartialDate(dd=18, mm=4)":13.551915,"PartialDate(dd=19, mm=4)":13.885324,"PartialDate(dd=20, mm=4)":13.814051,"PartialDate(dd=21, mm=4)":13.949675,"PartialDate(dd=22, mm=4)":13.949675,"PartialDate(dd=23, mm=4)":13.949675,"PartialDate(dd=24, mm=4)":13.227386,"PartialDate(dd=25, mm=4)":12.986358,"PartialDate(dd=26, mm=4)":12.679925,"PartialDate(dd=27, mm=4)":12.014301,"PartialDate(dd=28, mm=4)":11.085524,"PartialDate(dd=29, mm=4)":11.085524,"PartialDate(dd=30, mm=4)":11.085524,"PartialDate(dd=1, mm=5)":11.085524,"PartialDate(dd=2, mm=5)":10.544209,"PartialDate(dd=3, mm=5)":10.841327,"PartialDate(dd=4, mm=5)":9.930729,"PartialDate(dd=5, mm=5)":9.930729,"PartialDate(dd=6, mm=5)":9.930729,"PartialDate(dd=7, mm=5)":9.930729,"PartialDate(dd=8, mm=5)":9.676405,"PartialDate(dd=9, mm=5)":9.734989,"PartialDate(dd=10, mm=5)":9.462117,"PartialDate(dd=11, mm=5)":9.557248,"PartialDate(dd=12, mm=5)":9.423244,"PartialDate(dd=13, mm=5)":9.423244,"PartialDate(dd=14, mm=5)":9.423244,"PartialDate(dd=15, mm=5)":8.857358,"PartialDate(dd=16, mm=5)":9.160514,"PartialDate(dd=17, mm=5)":9.650382,"PartialDate(dd=18, mm=5)":10.043059,"PartialDate(dd=19, mm=5)":9.643881,"PartialDate(dd=20, mm=5)":9.643881,"PartialDate(dd=21, mm=5)":9.643881,"PartialDate(dd=22, mm=5)":9.264809,"PartialDate(dd=23, mm=5)":9.179849,"PartialDate(dd=24, mm=5)":9.471843,"PartialDate(dd=25, mm=5)":9.471843,"PartialDate(dd=26, mm=5)":8.198009,"PartialDate(dd=27, mm=5)":8.198009,"PartialDate(dd=28, mm=5)":8.198009,"PartialDate(dd=29, mm=5)":7.5611877,"PartialDate(dd=30, mm=5)":7.3332644,"PartialDate(dd=31, mm=5)":7.5465884,"PartialDate(dd=1, mm=6)":7.7680902,"PartialDate(dd=2, mm=6)":7.2813616,"PartialDate(dd=3, mm=6)":7.2813616,"PartialDate(dd=4, mm=6)":7.2813616,"PartialDate(dd=5, mm=6)":6.767151,"PartialDate(dd=6, mm=6)":6.497578,"PartialDate(dd=7, mm=6)":5.6808343,"PartialDate(dd=8, mm=6)":6.34239,"PartialDate(dd=9, mm=6)":6.6204114,"PartialDate(dd=10, mm=6)":6.6204114,"PartialDate(dd=11, mm=6)":6.6204114,"PartialDate(dd=12, mm=6)":6.364824,"PartialDate(dd=13, mm=6)":5.6697645,"PartialDate(dd=14, mm=6)":5.427729,"PartialDate(dd=15, mm=6)":5.653659,"PartialDate(dd=16, mm=6)":4.7586718,"PartialDate(dd=17, mm=6)":4.7586718,"PartialDate(dd=18, mm=6)":4.7586718,"PartialDate(dd=19, mm=6)":5.0592933,"PartialDate(dd=20, mm=6)":4.825985,"PartialDate(dd=21, mm=6)":4.922158,"PartialDate(dd=22, mm=6)":5.4939055,"PartialDate(dd=23, mm=6)":6.193761,"PartialDate(dd=24, mm=6)":6.193761,"PartialDate(dd=25, mm=6)":6.193761,"PartialDate(dd=26, mm=6)":5.9331408,"PartialDate(dd=27, mm=6)":5.307627,"PartialDate(dd=28, mm=6)":4.492234,"PartialDate(dd=29, mm=6)":4.492234,"PartialDate(dd=30, mm=6)":3.3166003,"PartialDate(dd=1, mm=7)":3.3166003,"PartialDate(dd=2, mm=7)":3.3166003,"PartialDate(dd=3, mm=7)":2.797684,"PartialDate(dd=4, mm=7)":2.6549869,"PartialDate(dd=5, mm=7)":2.577151,"PartialDate(dd=6, mm=7)":1.9839691,"PartialDate(dd=7, mm=7)":1.9839691,"PartialDate(dd=8, mm=7)":1.9839691,"PartialDate(dd=9, mm=7)":1.9839691,"PartialDate(dd=10, mm=7)":1.9839691,"PartialDate(dd=11, mm=7)":2.1022425,"PartialDate(dd=12, mm=7)":2.2999754,"PartialDate(dd=13, mm=7)":2.2566009,"PartialDate(dd=14, mm=7)":1.5247494,"PartialDate(dd=15, mm=7)":1.5247494,"PartialDate(dd=16, mm=7)":1.5247494,"PartialDate(dd=17, mm=7)":0.89315677,"PartialDate(dd=18, mm=7)":0.8372055,"PartialDate(dd=19, mm=7)":0.3945923,"PartialDate(dd=20, mm=7)":-0.22575578,"PartialDate(dd=21, mm=7)":0.6752214,"PartialDate(dd=22, mm=7)":0.6752214,"PartialDate(dd=23, mm=7)":0.6752214,"PartialDate(dd=24, mm=7)":1.0144297,"PartialDate(dd=25, mm=7)":0.9546724,"PartialDate(dd=26, mm=7)":0.48098794,"PartialDate(dd=27, mm=7)":0.7794913,"PartialDate(dd=28, mm=7)":0.63686144,"PartialDate(dd=29, mm=7)":0.63686144,"PartialDate(dd=30, mm=7)":0.63686144,"PartialDate(dd=31, mm=7)":0.056824595,"PartialDate(dd=1, mm=8)":0.12003882,"PartialDate(dd=2, mm=8)":1.3494405,"PartialDate(dd=3, mm=8)":1.864096,"PartialDate(dd=4, mm=8)":1.3883457,"PartialDate(dd=5, mm=8)":1.3883457,"PartialDate(dd=6, mm=8)":1.3883457,"PartialDate(dd=7, mm=8)":0.90049094,"PartialDate(dd=8, mm=8)":0.9923544,"PartialDate(dd=9, mm=8)":0.44732088,"PartialDate(dd=10, mm=8)":1.0751711,"PartialDate(dd=11, mm=8)":1.4096661,"PartialDate(dd=12, mm=8)":1.4096661,"PartialDate(dd=13, mm=8)":1.4096661,"PartialDate(dd=14, mm=8)":1.5572807,"PartialDate(dd=15, mm=8)":1.5572807,"PartialDate(dd=16, mm=8)":1.5572807,"PartialDate(dd=17, mm=8)":1.7902604,"PartialDate(dd=18, mm=8)":2.1238642,"PartialDate(dd=19, mm=8)":2.1238642,"PartialDate(dd=20, mm=8)":2.1238642,"PartialDate(dd=21, mm=8)":1.6307875,"PartialDate(dd=22, mm=8)":1.3735186,"PartialDate(dd=23, mm=8)":0.97673124,"PartialDate(dd=24, mm=8)":1.1452197,"PartialDate(dd=25, mm=8)":1.7837226,"PartialDate(dd=26, mm=8)":1.7837226,"PartialDate(dd=27, mm=8)":1.7837226,"PartialDate(dd=28, mm=8)":1.4866692,"PartialDate(dd=29, mm=8)":1.3216668,"PartialDate(dd=30, mm=8)":1.1525905,"PartialDate(dd=31, mm=8)":1.6354407,"PartialDate(dd=1, mm=9)":0.74288416,"PartialDate(dd=2, mm=9)":0.74288416,"PartialDate(dd=3, mm=9)":0.74288416,"PartialDate(dd=4, mm=9)":0.20686878,"PartialDate(dd=5, mm=9)":0.10106617,"PartialDate(dd=6, mm=9)":-0.00900893,"PartialDate(dd=7, mm=9)":-0.5914507,"PartialDate(dd=8, mm=9)":-1.2937789,"PartialDate(dd=9, mm=9)":-1.2937789,"PartialDate(dd=10, mm=9)":-1.2937789,"PartialDate(dd=11, mm=9)":-2.08315,"PartialDate(dd=12, mm=9)":-1.3280166,"PartialDate(dd=13, mm=9)":-1.6447152,"PartialDate(dd=14, mm=9)":-1.9827838,"PartialDate(dd=15, mm=9)":-2.326271,"PartialDate(dd=16, mm=9)":-2.326271,"PartialDate(dd=17, mm=9)":-2.326271,"PartialDate(dd=18, mm=9)":-2.14102,"PartialDate(dd=19, mm=9)":-2.14102,"PartialDate(dd=20, mm=9)":-1.1415943,"PartialDate(dd=21, mm=9)":-0.23113868,"PartialDate(dd=22, mm=9)":-0.13593256,"PartialDate(dd=23, mm=9)":-0.13593256,"PartialDate(dd=24, mm=9)":-0.13593256,"PartialDate(dd=25, mm=9)":-0.18266322,"PartialDate(dd=26, mm=9)":-0.1287387,"PartialDate(dd=27, mm=9)":-0.49603757,"PartialDate(dd=28, mm=9)":0.5010166,"PartialDate(dd=29, mm=9)":0.5010166,"PartialDate(dd=30, mm=9)":0.5010166,"PartialDate(dd=1, mm=10)":0.5010166,"PartialDate(dd=2, mm=10)":0.5010166,"PartialDate(dd=3, mm=10)":0.05772832,"PartialDate(dd=4, mm=10)":0.9307928,"PartialDate(dd=5, mm=10)":0.5283335,"PartialDate(dd=6, mm=10)":-0.060358047,"PartialDate(dd=7, mm=10)":-0.060358047,"PartialDate(dd=8, mm=10)":-0.060358047,"PartialDate(dd=9, mm=10)":0.6724854,"PartialDate(dd=10, mm=10)":-0.2903292,"PartialDate(dd=11, mm=10)":-0.785275,"PartialDate(dd=12, mm=10)":-0.7204515,"PartialDate(dd=13, mm=10)":-0.6671066,"PartialDate(dd=14, mm=10)":-0.6671066,"PartialDate(dd=15, mm=10)":-0.6671066,"PartialDate(dd=16, mm=10)":-0.6822291,"PartialDate(dd=17, mm=10)":-0.96773076,"PartialDate(dd=18, mm=10)":-0.23383418,"PartialDate(dd=19, mm=10)":0.0,"PartialDate(dd=20, mm=10)":0.0,"PartialDate(dd=21, mm=10)":5.465002,"PartialDate(dd=22, mm=10)":5.465002,"PartialDate(dd=23, mm=10)":5.465002,"PartialDate(dd=24, mm=10)":5.465002,"PartialDate(dd=25, mm=10)":5.465002,"PartialDate(dd=26, mm=10)":5.465002,"PartialDate(dd=27, mm=10)":5.465002,"PartialDate(dd=28, mm=10)":5.458904,"PartialDate(dd=29, mm=10)":5.458904,"PartialDate(dd=30, mm=10)":5.458904,"PartialDate(dd=31, mm=10)":5.4350686,"PartialDate(dd=1, mm=11)":5.259437,"PartialDate(dd=2, mm=11)":5.366448,"PartialDate(dd=3, mm=11)":5.465002,"PartialDate(dd=4, mm=11)":5.311239,"PartialDate(dd=5, mm=11)":5.311239,"PartialDate(dd=6, mm=11)":5.311239,"PartialDate(dd=7, mm=11)":5.0455575,"PartialDate(dd=8, mm=11)":5.0455575,"PartialDate(dd=9, mm=11)":5.174783,"PartialDate(dd=10, mm=11)":5.5811653,"PartialDate(dd=11, mm=11)":4.7321405,"PartialDate(dd=12, mm=11)":4.7321405,"PartialDate(dd=13, mm=11)":4.7321405,"PartialDate(dd=14, mm=11)":4.78512,"PartialDate(dd=15, mm=11)":4.5770354,"PartialDate(dd=16, mm=11)":4.5716634,"PartialDate(dd=17, mm=11)":4.7569933,"PartialDate(dd=18, mm=11)":4.859897,"PartialDate(dd=19, mm=11)":4.859897,"PartialDate(dd=20, mm=11)":4.859897,"PartialDate(dd=21, mm=11)":5.2715526,"PartialDate(dd=22, mm=11)":5.033541,"PartialDate(dd=23, mm=11)":5.033541,"PartialDate(dd=24, mm=11)":4.355606,"PartialDate(dd=25, mm=11)":4.273165,"PartialDate(dd=26, mm=11)":4.273165,"PartialDate(dd=27, mm=11)":4.273165,"PartialDate(dd=28, mm=11)":4.139136,"PartialDate(dd=29, mm=11)":3.9737062,"PartialDate(dd=30, mm=11)":3.5898902,"PartialDate(dd=1, mm=12)":3.7373471,"PartialDate(dd=2, mm=12)":3.9270034,"PartialDate(dd=3, mm=12)":3.9270034,"PartialDate(dd=4, mm=12)":3.9270034,"PartialDate(dd=5, mm=12)":3.8746214,"PartialDate(dd=6, mm=12)":4.028911,"PartialDate(dd=7, mm=12)":4.248744,"PartialDate(dd=8, mm=12)":4.1153646,"PartialDate(dd=9, mm=12)":4.420668,"PartialDate(dd=10, mm=12)":4.420668,"PartialDate(dd=11, mm=12)":4.420668,"PartialDate(dd=12, mm=12)":4.419604,"PartialDate(dd=13, mm=12)":4.111668,"PartialDate(dd=14, mm=12)":3.9668798,"PartialDate(dd=15, mm=12)":4.6550145,"PartialDate(dd=16, mm=12)":5.074524,"PartialDate(dd=17, mm=12)":5.074524,"PartialDate(dd=18, mm=12)":5.074524,"PartialDate(dd=19, mm=12)":4.642629,"PartialDate(dd=20, mm=12)":4.7397027,"PartialDate(dd=21, mm=12)":5.274305,"PartialDate(dd=22, mm=12)":5.481648,"PartialDate(dd=23, mm=12)":6.424789,"PartialDate(dd=24, mm=12)":6.424789,"PartialDate(dd=25, mm=12)":6.424789,"PartialDate(dd=26, mm=12)":5.8093452,"PartialDate(dd=27, mm=12)":5.467774,"PartialDate(dd=28, mm=12)":5.496636,"PartialDate(dd=29, mm=12)":5.2930393,"PartialDate(dd=30, mm=12)":5.5371976,"PartialDate(dd=31, mm=12)":5.5371976},"2022":{"PartialDate(dd=21, mm=10)":10.930004,"PartialDate(dd=22, mm=10)":10.930004,"PartialDate(dd=23, mm=10)":10.930004,"PartialDate(dd=24, mm=10)":10.930004,"PartialDate(dd=25, mm=10)":10.930004,"PartialDate(dd=26, mm=10)":10.930004,"PartialDate(dd=27, mm=10)":10.930004,"PartialDate(dd=28, mm=10)":10.917808,"PartialDate(dd=29, mm=10)":10.917808,"PartialDate(dd=30, mm=10)":10.917808,"PartialDate(dd=31, mm=10)":10.870137,"PartialDate(dd=1, mm=11)":10.518874,"PartialDate(dd=2, mm=11)":10.732896,"PartialDate(dd=3, mm=11)":10.930004,"PartialDate(dd=4, mm=11)":10.622478,"PartialDate(dd=5, mm=11)":10.622478,"PartialDate(dd=6, mm=11)":10.622478,"PartialDate(dd=7, mm=11)":10.091115,"PartialDate(dd=8, mm=11)":10.091115,"PartialDate(dd=9, mm=11)":10.349566,"PartialDate(dd=10, mm=11)":11.162331,"PartialDate(dd=11, mm=11)":9.464281,"PartialDate(dd=12, mm=11)":9.464281,"PartialDate(dd=13, mm=11)":9.464281,"PartialDate(dd=14, mm=11)":9.57024,"PartialDate(dd=15, mm=11)":9.154071,"PartialDate(dd=16, mm=11)":9.143327,"PartialDate(dd=17, mm=11)":9.513987,"PartialDate(dd=18, mm=11)":9.719794,"PartialDate(dd=19, mm=11)":9.719794,"PartialDate(dd=20, mm=11)":9.719794,"PartialDate(dd=21, mm=11)":10.543105,"PartialDate(dd=22, mm=11)":10.067082,"PartialDate(dd=23, mm=11)":10.067082,"PartialDate(dd=24, mm=11)":8.711212,"PartialDate(dd=25, mm=11)":8.54633,"PartialDate(dd=26, mm=11)":8.54633,"PartialDate(dd=27, mm=11)":8.54633,"PartialDate(dd=28, mm=11)":8.278272,"PartialDate(dd=29, mm=11)":7.9474125,"PartialDate(dd=30, mm=11)":7.1797805,"PartialDate(dd=1, mm=12)":7.4746943,"PartialDate(dd=2, mm=12)":7.854007,"PartialDate(dd=3, mm=12)":7.854007,"PartialDate(dd=4, mm=12)":7.854007,"PartialDate(dd=5, mm=12)":7.749243,"PartialDate(dd=6, mm=12)":8.057822,"PartialDate(dd=7, mm=12)":8.497488,"PartialDate(dd=8, mm=12)":8.230729,"PartialDate(dd=9, mm=12)":8.841336,"PartialDate(dd=10, mm=12)":8.841336,"PartialDate(dd=11, mm=12)":8.841336,"PartialDate(dd=12, mm=12)":8.839208,"PartialDate(dd=13, mm=12)":8.223336,"PartialDate(dd=14, mm=12)":7.9337597,"PartialDate(dd=15, mm=12)":9.310029,"PartialDate(dd=16, mm=12)":10.149048,"PartialDate(dd=17, mm=12)":10.149048,"PartialDate(dd=18, mm=12)":10.149048,"PartialDate(dd=19, mm=12)":9.285258,"PartialDate(dd=20, mm=12)":9.479405,"PartialDate(dd=21, mm=12)":10.54861,"PartialDate(dd=22, mm=12)":10.963296,"PartialDate(dd=23, mm=12)":12.849578,"PartialDate(dd=24, mm=12)":12.849578,"PartialDate(dd=25, mm=12)":12.849578,"PartialDate(dd=26, mm=12)":11.6186905,"PartialDate(dd=27, mm=12)":10.935548,"PartialDate(dd=28, mm=12)":10.993272,"PartialDate(dd=29, mm=12)":10.586079,"PartialDate(dd=30, mm=12)":11.074395,"PartialDate(dd=31, mm=12)":11.074395},"2023":{"PartialDate(dd=1, mm=1)":11.074395,"PartialDate(dd=2, mm=1)":10.546404,"PartialDate(dd=3, mm=1)":10.347367,"PartialDate(dd=4, mm=1)":11.450473,"PartialDate(dd=5, mm=1)":11.760382,"PartialDate(dd=6, mm=1)":12.541599,"PartialDate(dd=7, mm=1)":12.541599,"PartialDate(dd=8, mm=1)":12.541599,"PartialDate(dd=9, mm=1)":11.1267,"PartialDate(dd=10, mm=1)":12.231895,"PartialDate(dd=11, mm=1)":12.343284,"PartialDate(dd=12, mm=1)":12.5621605,"PartialDate(dd=13, mm=1)":11.969079,"PartialDate(dd=14, mm=1)":11.969079,"PartialDate(dd=15, mm=1)":11.969079,"PartialDate(dd=16, mm=1)":12.330765,"PartialDate(dd=17, mm=1)":11.390043,"PartialDate(dd=18, mm=1)":10.734003,"PartialDate(dd=19, mm=1)":11.062167,"PartialDate(dd=20, mm=1)":11.534524,"PartialDate(dd=21, mm=1)":11.534524,"PartialDate(dd=22, mm=1)":11.534524,"PartialDate(dd=23, mm=1)":10.99216,"PartialDate(dd=24, mm=1)":10.989936,"PartialDate(dd=25, mm=1)":12.313714,"PartialDate(dd=26, mm=1)":12.313714,"PartialDate(dd=27, mm=1)":14.035179,"PartialDate(dd=28, mm=1)":14.035179,"PartialDate(dd=29, mm=1)":14.035179,"PartialDate(dd=30, mm=1)":13.745202,"PartialDate(dd=31, mm=1)":13.697394,"PartialDate(dd=1, mm=2)":13.546108,"PartialDate(dd=2, mm=2)":13.282887,"PartialDate(dd=3, mm=2)":11.857302,"PartialDate(dd=4, mm=2)":11.857302,"PartialDate(dd=5, mm=2)":11.857302,"PartialDate(dd=6, mm=2)":12.445773,"PartialDate(dd=7, mm=2)":12.804817,"PartialDate(dd=8, mm=2)":12.064094,"PartialDate(dd=9, mm=2)":11.809949,"PartialDate(dd=10, mm=2)":12.025618,"PartialDate(dd=11, mm=2)":12.025618,"PartialDate(dd=12, mm=2)":12.025618,"PartialDate(dd=13, mm=2)":12.490239,"PartialDate(dd=14, mm=2)":11.536769,"PartialDate(dd=15, mm=2)":10.928893,"PartialDate(dd=16, mm=2)":10.8313675,"PartialDate(dd=17, mm=2)":11.358733,"PartialDate(dd=18, mm=2)":11.358733,"PartialDate(dd=19, mm=2)":11.358733,"PartialDate(dd=20, mm=2)":11.955522,"PartialDate(dd=21, mm=2)":12.060694,"PartialDate(dd=22, mm=2)":13.714878,"PartialDate(dd=23, mm=2)":13.997684,"PartialDate(dd=24, mm=2)":14.272468,"PartialDate(dd=25, mm=2)":14.272468,"PartialDate(dd=26, mm=2)":14.272468,"PartialDate(dd=27, mm=2)":14.677674,"PartialDate(dd=28, mm=2)":15.380221,"PartialDate(dd=1, mm=3)":14.467035,"PartialDate(dd=2, mm=3)":15.347831,"PartialDate(dd=3, mm=3)":13.730033,"PartialDate(dd=4, mm=3)":13.730033,"PartialDate(dd=5, mm=3)":13.730033,"PartialDate(dd=6, mm=3)":13.042775,"PartialDate(dd=7, mm=3)":13.042775,"PartialDate(dd=8, mm=3)":12.80253,"PartialDate(dd=9, mm=3)":13.838577,"PartialDate(dd=10, mm=3)":14.954558,"PartialDate(dd=11, mm=3)":14.954558,"PartialDate(dd=12, mm=3)":14.954558,"PartialDate(dd=13, mm=3)":16.703321,"PartialDate(dd=14, mm=3)":17.387493,"PartialDate(dd=15, mm=3)":17.93913,"PartialDate(dd=16, mm=3)":17.860186,"PartialDate(dd=17, mm=3)":17.093819,"PartialDate(dd=18, mm=3)":17.093819,"PartialDate(dd=19, mm=3)":17.093819,"PartialDate(dd=20, mm=3)":17.836391,"PartialDate(dd=21, mm=3)":17.008598,"PartialDate(dd=22, mm=3)":17.008598,"PartialDate(dd=23, mm=3)":17.15071,"PartialDate(dd=24, mm=3)":18.055851,"PartialDate(dd=25, mm=3)":18.055851,"PartialDate(dd=26, mm=3)":18.055851,"PartialDate(dd=27, mm=3)":17.78885,"PartialDate(dd=28, mm=3)":17.984291,"PartialDate(dd=29, mm=3)":17.169271,"PartialDate(dd=30, mm=3)":17.169271,"PartialDate(dd=31, mm=3)":15.352624,"PartialDate(dd=1, mm=4)":15.352624,"PartialDate(dd=2, mm=4)":15.352624,"PartialDate(dd=3, mm=4)":15.040396,"PartialDate(dd=4, mm=4)":15.040396,"PartialDate(dd=5, mm=4)":14.117297,"PartialDate(dd=6, mm=4)":13.893508,"PartialDate(dd=7, mm=4)":13.893508,"PartialDate(dd=8, mm=4)":13.893508,"PartialDate(dd=9, mm=4)":13.893508,"PartialDate(dd=10, mm=4)":13.782532,"PartialDate(dd=11, mm=4)":13.16386,"PartialDate(dd=12, mm=4)":12.705112,"PartialDate(dd=13, mm=4)":12.596429,"PartialDate(dd=14, mm=4)":12.596429,"PartialDate(dd=15, mm=4)":12.596429,"PartialDate(dd=16, mm=4)":12.596429,"PartialDate(dd=17, mm=4)":13.279423,"PartialDate(dd=18, mm=4)":13.551915,"PartialDate(dd=19, mm=4)":13.885324,"PartialDate(dd=20, mm=4)":13.814051,"PartialDate(dd=21, mm=4)":13.949675,"PartialDate(dd=22, mm=4)":13.949675,"PartialDate(dd=23, mm=4)":13.949675,"PartialDate(dd=24, mm=4)":13.227386,"PartialDate(dd=25, mm=4)":12.986358,"PartialDate(dd=26, mm=4)":12.679925,"PartialDate(dd=27, mm=4)":12.014301,"PartialDate(dd=28, mm=4)":11.085524,"PartialDate(dd=29, mm=4)":11.085524,"PartialDate(dd=30, mm=4)":11.085524,"PartialDate(dd=1, mm=5)":11.085524,"PartialDate(dd=2, mm=5)":10.544209,"PartialDate(dd=3, mm=5)":10.841327,"PartialDate(dd=4, mm=5)":9.930729,"PartialDate(dd=5, mm=5)":9.930729,"PartialDate(dd=6, mm=5)":9.930729,"PartialDate(dd=7, mm=5)":9.930729,"PartialDate(dd=8, mm=5)":9.676405,"PartialDate(dd=9, mm=5)":9.734989,"PartialDate(dd=10, mm=5)":9.462117,"PartialDate(dd=11, mm=5)":9.557248,"PartialDate(dd=12, mm=5)":9.423244,"PartialDate(dd=13, mm=5)":9.423244,"PartialDate(dd=14, mm=5)":9.423244,"PartialDate(dd=15, mm=5)":8.857358,"PartialDate(dd=16, mm=5)":9.160514,"PartialDate(dd=17, mm=5)":9.650382,"PartialDate(dd=18, mm=5)":10.043059,"PartialDate(dd=19, mm=5)":9.643881,"PartialDate(dd=20, mm=5)":9.643881,"PartialDate(dd=21, mm=5)":9.643881,"PartialDate(dd=22, mm=5)":9.264809,"PartialDate(dd=23, mm=5)":9.179849,"PartialDate(dd=24, mm=5)":9.471843,"PartialDate(dd=25, mm=5)":9.471843,"PartialDate(dd=26, mm=5)":8.198009,"PartialDate(dd=27, mm=5)":8.198009,"PartialDate(dd=28, mm=5)":8.198009,"PartialDate(dd=29, mm=5)":7.5611877,"PartialDate(dd=30, mm=5)":7.3332644,"PartialDate(dd=31, mm=5)":7.5465884,"PartialDate(dd=1, mm=6)":7.7680902,"PartialDate(dd=2, mm=6)":7.2813616,"PartialDate(dd=3, mm=6)":7.2813616,"PartialDate(dd=4, mm=6)":7.2813616,"PartialDate(dd=5, mm=6)":6.767151,"PartialDate(dd=6, mm=6)":6.497578,"PartialDate(dd=7, mm=6)":5.6808343,"PartialDate(dd=8, mm=6)":6.34239,"PartialDate(dd=9, mm=6)":6.6204114,"PartialDate(dd=10, mm=6)":6.6204114,"PartialDate(dd=11, mm=6)":6.6204114,"PartialDate(dd=12, mm=6)":6.364824,"PartialDate(dd=13, mm=6)":5.6697645,"PartialDate(dd=14, mm=6)":5.427729,"PartialDate(dd=15, mm=6)":5.653659,"PartialDate(dd=16, mm=6)":4.7586718,"PartialDate(dd=17, mm=6)":4.7586718,"PartialDate(dd=18, mm=6)":4.7586718,"PartialDate(dd=19, mm=6)":5.0592933,"PartialDate(dd=20, mm=6)":4.825985,"PartialDate(dd=21, mm=6)":4.922158,"PartialDate(dd=22, mm=6)":5.4939055,"PartialDate(dd=23, mm=6)":6.193761,"PartialDate(dd=24, mm=6)":6.193761,"PartialDate(dd=25, mm=6)":6.193761,"PartialDate(dd=26, mm=6)":5.9331408,"PartialDate(dd=27, mm=6)":5.307627,"PartialDate(dd=28, mm=6)":4.492234,"PartialDate(dd=29, mm=6)":4.492234,"PartialDate(dd=30, mm=6)":3.3166003,"PartialDate(dd=1, mm=7)":3.3166003,"PartialDate(dd=2, mm=7)":3.3166003,"PartialDate(dd=3, mm=7)":2.797684,"PartialDate(dd=4, mm=7)":2.6549869,"PartialDate(dd=5, mm=7)":2.577151,"PartialDate(dd=6, mm=7)":1.9839691,"PartialDate(dd=7, mm=7)":1.9839691,"PartialDate(dd=8, mm=7)":1.9839691,"PartialDate(dd=9, mm=7)":1.9839691,"PartialDate(dd=10, mm=7)":1.9839691,"PartialDate(dd=11, mm=7)":2.1022425,"PartialDate(dd=12, mm=7)":2.2999754,"PartialDate(dd=13, mm=7)":2.2566009,"PartialDate(dd=14, mm=7)":1.5247494,"PartialDate(dd=15, mm=7)":1.5247494,"PartialDate(dd=16, mm=7)":1.5247494,"PartialDate(dd=17, mm=7)":0.89315677,"PartialDate(dd=18, mm=7)":0.8372055,"PartialDate(dd=19, mm=7)":0.3945923,"PartialDate(dd=20, mm=7)":-0.22575578,"PartialDate(dd=21, mm=7)":0.6752214,"PartialDate(dd=22, mm=7)":0.6752214,"PartialDate(dd=23, mm=7)":0.6752214,"PartialDate(dd=24, mm=7)":1.0144297,"PartialDate(dd=25, mm=7)":0.9546724,"PartialDate(dd=26, mm=7)":0.48098794,"PartialDate(dd=27, mm=7)":0.7794913,"PartialDate(dd=28, mm=7)":0.63686144,"PartialDate(dd=29, mm=7)":0.63686144,"PartialDate(dd=30, mm=7)":0.63686144,"PartialDate(dd=31, mm=7)":0.056824595,"PartialDate(dd=1, mm=8)":0.12003882,"PartialDate(dd=2, mm=8)":1.3494405,"PartialDate(dd=3, mm=8)":1.864096,"PartialDate(dd=4, mm=8)":1.3883457,"PartialDate(dd=5, mm=8)":1.3883457,"PartialDate(dd=6, mm=8)":1.3883457,"PartialDate(dd=7, mm=8)":0.90049094,"PartialDate(dd=8, mm=8)":0.9923544,"PartialDate(dd=9, mm=8)":0.44732088,"PartialDate(dd=10, mm=8)":1.0751711,"PartialDate(dd=11, mm=8)":1.4096661,"PartialDate(dd=12, mm=8)":1.4096661,"PartialDate(dd=13, mm=8)":1.4096661,"PartialDate(dd=14, mm=8)":1.5572807,"PartialDate(dd=15, mm=8)":1.5572807,"PartialDate(dd=16, mm=8)":1.5572807,"PartialDate(dd=17, mm=8)":1.7902604,"PartialDate(dd=18, mm=8)":2.1238642,"PartialDate(dd=19, mm=8)":2.1238642,"PartialDate(dd=20, mm=8)":2.1238642,"PartialDate(dd=21, mm=8)":1.6307875,"PartialDate(dd=22, mm=8)":1.3735186,"PartialDate(dd=23, mm=8)":0.97673124,"PartialDate(dd=24, mm=8)":1.1452197,"PartialDate(dd=25, mm=8)":1.7837226,"PartialDate(dd=26, mm=8)":1.7837226,"PartialDate(dd=27, mm=8)":1.7837226,"PartialDate(dd=28, mm=8)":1.4866692,"PartialDate(dd=29, mm=8)":1.3216668,"PartialDate(dd=30, mm=8)":1.1525905,"PartialDate(dd=31, mm=8)":1.6354407,"PartialDate(dd=1, mm=9)":0.74288416,"PartialDate(dd=2, mm=9)":0.74288416,"PartialDate(dd=3, mm=9)":0.74288416,"PartialDate(dd=4, mm=9)":0.20686878,"PartialDate(dd=5, mm=9)":0.10106617,"PartialDate(dd=6, mm=9)":-0.00900893,"PartialDate(dd=7, mm=9)":-0.5914507,"PartialDate(dd=8, mm=9)":-1.2937789,"PartialDate(dd=9, mm=9)":-1.2937789,"PartialDate(dd=10, mm=9)":-1.2937789,"PartialDate(dd=11, mm=9)":-2.08315,"PartialDate(dd=12, mm=9)":-1.3280166,"PartialDate(dd=13, mm=9)":-1.6447152,"PartialDate(dd=14, mm=9)":-1.9827838,"PartialDate(dd=15, mm=9)":-2.326271,"PartialDate(dd=16, mm=9)":-2.326271,"PartialDate(dd=17, mm=9)":-2.326271,"PartialDate(dd=18, mm=9)":-2.14102,"PartialDate(dd=19, mm=9)":-2.14102,"PartialDate(dd=20, mm=9)":-1.1415943,"PartialDate(dd=21, mm=9)":-0.23113868,"PartialDate(dd=22, mm=9)":-0.13593256,"PartialDate(dd=23, mm=9)":-0.13593256,"PartialDate(dd=24, mm=9)":-0.13593256,"PartialDate(dd=25, mm=9)":-0.18266322,"PartialDate(dd=26, mm=9)":-0.1287387,"PartialDate(dd=27, mm=9)":-0.49603757,"PartialDate(dd=28, mm=9)":0.5010166,"PartialDate(dd=29, mm=9)":0.5010166,"PartialDate(dd=30, mm=9)":0.5010166,"PartialDate(dd=1, mm=10)":0.5010166,"PartialDate(dd=2, mm=10)":0.5010166,"PartialDate(dd=3, mm=10)":0.05772832,"PartialDate(dd=4, mm=10)":0.9307928,"PartialDate(dd=5, mm=10)":0.5283335,"PartialDate(dd=6, mm=10)":-0.060358047,"PartialDate(dd=7, mm=10)":-0.060358047,"PartialDate(dd=8, mm=10)":-0.060358047,"PartialDate(dd=9, mm=10)":0.6724854,"PartialDate(dd=10, mm=10)":-0.2903292,"PartialDate(dd=11, mm=10)":-0.785275,"PartialDate(dd=12, mm=10)":-0.7204515,"PartialDate(dd=13, mm=10)":-0.6671066,"PartialDate(dd=14, mm=10)":-0.6671066,"PartialDate(dd=15, mm=10)":-0.6671066,"PartialDate(dd=16, mm=10)":-0.6822291,"PartialDate(dd=17, mm=10)":-0.96773076,"PartialDate(dd=18, mm=10)":-0.23383418,"PartialDate(dd=19, mm=10)":0.0,"PartialDate(dd=20, mm=10)":0.0,"PartialDate(dd=21, mm=10)":0.0,"PartialDate(dd=22, mm=10)":0.0,"PartialDate(dd=23, mm=10)":0.0,"PartialDate(dd=24, mm=10)":0.0,"PartialDate(dd=25, mm=10)":0.0,"PartialDate(dd=26, mm=10)":0.0,"PartialDate(dd=27, mm=10)":0.0,"PartialDate(dd=28, mm=10)":0.0,"PartialDate(dd=29, mm=10)":0.0,"PartialDate(dd=30, mm=10)":0.0,"PartialDate(dd=31, mm=10)":0.0,"PartialDate(dd=1, mm=11)":0.0,"PartialDate(dd=2, mm=11)":0.0,"PartialDate(dd=3, mm=11)":0.0,"PartialDate(dd=4, mm=11)":0.0,"PartialDate(dd=5, mm=11)":0.0,"PartialDate(dd=6, mm=11)":0.0,"PartialDate(dd=7, mm=11)":0.0,"PartialDate(dd=8, mm=11)":0.0,"PartialDate(dd=9, mm=11)":0.0,"PartialDate(dd=10, mm=11)":0.0,"PartialDate(dd=11, mm=11)":0.0,"PartialDate(dd=12, mm=11)":0.0,"PartialDate(dd=13, mm=11)":0.0,"PartialDate(dd=14, mm=11)":0.0,"PartialDate(dd=15, mm=11)":0.0,"PartialDate(dd=16, mm=11)":0.0,"PartialDate(dd=17, mm=11)":0.0,"PartialDate(dd=18, mm=11)":0.0,"PartialDate(dd=19, mm=11)":0.0,"PartialDate(dd=20, mm=11)":0.0,"PartialDate(dd=21, mm=11)":0.0,"PartialDate(dd=22, mm=11)":0.0,"PartialDate(dd=23, mm=11)":0.0,"PartialDate(dd=24, mm=11)":0.0,"PartialDate(dd=25, mm=11)":0.0,"PartialDate(dd=26, mm=11)":0.0,"PartialDate(dd=27, mm=11)":0.0,"PartialDate(dd=28, mm=11)":0.0,"PartialDate(dd=29, mm=11)":0.0,"PartialDate(dd=30, mm=11)":0.0,"PartialDate(dd=1, mm=12)":0.0,"PartialDate(dd=2, mm=12)":0.0,"PartialDate(dd=3, mm=12)":0.0,"PartialDate(dd=4, mm=12)":0.0,"PartialDate(dd=5, mm=12)":0.0,"PartialDate(dd=6, mm=12)":0.0,"PartialDate(dd=7, mm=12)":0.0,"PartialDate(dd=8, mm=12)":0.0,"PartialDate(dd=9, mm=12)":0.0,"PartialDate(dd=10, mm=12)":0.0,"PartialDate(dd=11, mm=12)":0.0,"PartialDate(dd=12, mm=12)":0.0,"PartialDate(dd=13, mm=12)":0.0,"PartialDate(dd=14, mm=12)":0.0,"PartialDate(dd=15, mm=12)":0.0,"PartialDate(dd=16, mm=12)":0.0,"PartialDate(dd=17, mm=12)":0.0,"PartialDate(dd=18, mm=12)":0.0,"PartialDate(dd=19, mm=12)":0.0,"PartialDate(dd=20, mm=12)":0.0,"PartialDate(dd=21, mm=12)":0.0,"PartialDate(dd=22, mm=12)":0.0,"PartialDate(dd=23, mm=12)":0.0,"PartialDate(dd=24, mm=12)":0.0,"PartialDate(dd=25, mm=12)":0.0,"PartialDate(dd=26, mm=12)":0.0,"PartialDate(dd=27, mm=12)":0.0,"PartialDate(dd=28, mm=12)":0.0,"PartialDate(dd=29, mm=12)":0.0,"PartialDate(dd=30, mm=12)":0.0,"PartialDate(dd=31, mm=12)":0.0}}